zpp_serpent/__init__.py
zpp_serpent/serpent.py
zpp_serpent-2.2.2.dist-info/METADATA
zpp_serpent-2.2.2.dist-info/WHEEL
zpp_serpent-2.2.2.dist-info/top_level.txt
zpp_serpent-2.2.2.dist-info/RECORD
