Metadata-Version: 2.1
Name: zpp-serpent
Version: 2.2.2
Summary: Implémentation de l'algorithme de chiffrement Serpent en python3
Home-page: https://github.com/ZephyrOff/py-zpp_serpent
Author: ZephyrOff
Author-email: contact@apajak.fr
License: MIT
Keywords: cipher chiffrement serpent zephyroff
Platform: ALL
Classifier: Development Status :: 5 - Production/Stable
Classifier: Environment :: Console
Classifier: License :: OSI Approved :: MIT License
Classifier: Programming Language :: Python :: 3
Requires-Dist: bitstring
